odoo/addons/mrp_bom_location/README.rst
odoo/addons/mrp_bom_location/__init__.py
odoo/addons/mrp_bom_location/__manifest__.py
odoo/addons/mrp_bom_location/i18n/de.po
odoo/addons/mrp_bom_location/i18n/mrp_bom_location.pot
odoo/addons/mrp_bom_location/models/__init__.py
odoo/addons/mrp_bom_location/models/mrp_bom.py
odoo/addons/mrp_bom_location/report/__init__.py
odoo/addons/mrp_bom_location/report/bom_structure.py
odoo/addons/mrp_bom_location/static/description/icon.png
odoo/addons/mrp_bom_location/views/mrp_view.xml
odoo/addons/mrp_bom_location/views/report_mrpbomstructure.xml
odoo11_addon_mrp_bom_location-11.0.1.0.0.99.dev6.dist-info/METADATA
odoo11_addon_mrp_bom_location-11.0.1.0.0.99.dev6.dist-info/RECORD
odoo11_addon_mrp_bom_location-11.0.1.0.0.99.dev6.dist-info/WHEEL
odoo11_addon_mrp_bom_location-11.0.1.0.0.99.dev6.dist-info/top_level.txt
